{
    "affinities": {
        "Alarm": {
            "Alarm Time Preference": "8:30 AM",
            "Alarm Sound Preference": "gentle nature",
            "Alarm Recurring Preference": "weekdays"
        },
        "Books": {
            "Genre": [
                "history",
                "non-fiction",
                "biography"
            ],
            "Favourite Authors": [
                "Yuval Noah Harari",
                "Amos Oz",
                "Sami Michael"
            ],
            "Favourite Books": [
                "Sapiens: A Brief History of Humankind",
                "A Tale of Love and Darkness",
                "Victoria"
            ],
            "Favourite Book Series": [
                "The Century Trilogy by Ken Follett"
            ],
            "Reading Format": [
                "physical",
                "ebook"
            ],
            "Reading Time Preference": [
                "evening"
            ],
            "Reading Frequency": "weekly"
        },
        "Buses": {
            "Preferred Bus Company": [
                "Egged",
                "Dan"
            ],
            "Travel Frequency": [
                "weekly",
                "monthly"
            ],
            "Seat Preference": "window",
            "Departure Time Preference": [
                "morning",
                "afternoon"
            ]
        },
        "Calendar": {
            "Event Type Preference": [
                "family gatherings",
                "social events",
                "work meetings"
            ],
            "Notification Preference": "1 day before",
            "Timezone": "UTC+2"
        },
        "Events": {
            "Event Type Preference": [
                "cultural celebrations",
                "food and drink tastings",
                "art exhibitions",
                "workshops",
                "lectures"
            ],
            "Price Range": [
                "under $50",
                "free"
            ],
            "Group Size Preference": "small group",
            "Seating Preference": [
                "general admission"
            ],
            "Days of Week Preference": "weekends"
        },
        "Finance": {
            "Preferred Sectors": [
                "technology",
                "healthcare",
                "consumer goods"
            ],
            "News Sources": [
                "financial news channels",
                "investment newsletters",
                "financial websites",
                "professional analyses"
            ],
            "Financial Company": [
                "Apple",
                "Pfizer",
                "Unilever",
                "Local Israeli Tech Startups"
            ]
        },
        "Flights": {
            "Preferred Airline": [
                "El Al",
                "Turkish Airlines",
                "Emirates"
            ],
            "Seat Class Preference": [
                "economy",
                "premium economy"
            ],
            "Layover Preference": [
                "short layover",
                "non-stop"
            ],
            "Seat Preference": "aisle",
            "Departure Time Preference": [
                "morning",
                "afternoon"
            ]
        },
        "Games": {
            "Preferred Game Genres": [
                "strategy",
                "simulation",
                "RPG",
                "puzzle"
            ],
            "Gaming Platforms": [
                "PC",
                "mobile"
            ],
            "Multiplayer Preference": [
                "single player",
                "online multiplayer"
            ],
            "Gaming Frequency": [
                "2-3 times per week",
                "1-2 hours per session"
            ],
            "Preferred Game Name": [
                "Civilization VI",
                "Cities: Skylines",
                "The Witcher 3",
                "Portal 2"
            ]
        },
        "Hotels": {
            "Hotel Chains Preference": [
                "Radisson",
                "Hyatt",
                "Intercontinental"
            ],
            "Amenity Preference": [
                "WiFi",
                "free breakfast",
                "pool",
                "gym",
                "bar/lounge"
            ],
            "Location Preference": [
                "city center",
                "near cultural landmarks",
                "near shopping districts"
            ],
            "Star Rating Preference": [
                "4 star",
                "5 star"
            ],
            "Room Type Preference": [
                "double",
                "suite"
            ]
        },
        "Media": {
            "Preferred Genres": [
                "drama",
                "historical fiction",
                "foreign film",
                "independent"
            ],
            "Favourite Actors and Directors": [
                "Asghar Farhadi",
                "Golshifteh Farahani",
                "Navid Mohammadzadeh"
            ],
            "Favourite Media": [
                "A Separation",
                "The Salesman",
                "Persepolis"
            ],
            "Viewing Platform Preference": [
                "Netflix",
                "Amazon Prime",
                "Kanopy"
            ]
        },
        "Messaging": {
            "Preferred Messaging Apps": [
                "WhatsApp",
                "Facebook Messenger",
                "Telegram"
            ],
            "Communication Style": "text",
            "Frequent Contact": [
                "family members",
                "close friends"
            ],
            "Preferred Communication Style": "casual"
        },
        "Movies": {
            "Preferred Genres": [
                "drama",
                "foreign film",
                "historical fiction",
                "independent"
            ],
            "Favorite Actors and Directors": [
                "Amos Gitai",
                "Natalie Portman",
                "Gal Gadot"
            ],
            "Theater Type Preference": [
                "standard",
                "open-air cinema"
            ],
            "Viewing Time Preference": [
                "weekends only",
                "during vacations",
                "evening"
            ],
            "Seat Type Preference": [
                "middle row",
                "aisle"
            ]
        },
        "Music": {
            "Preferred Genres": [
                "rock",
                "metal",
                "electronic",
                "world"
            ],
            "Favorite Artists": [
                "Orphaned Land",
                "Lenny Kravitz",
                "Infected Mushroom"
            ],
            "Favorite Bands": [
                "Orphaned Land",
                "Mashina"
            ],
            "Favorite Albums": [
                "El Norra Alila",
                "Mabool",
                "Classical Mushroom"
            ],
            "Platform Preference": [
                "Spotify",
                "YouTube Music"
            ],
            "Preferred Audio Quality": "high definition",
            "Playlist Preference": [
                "workout playlists",
                "playlists for studying",
                "playlists combining different genres"
            ]
        },
        "Rental Cars": {
            "Car Type Preference": [
                "SUV",
                "premium"
            ],
            "Preferred Rental Company": [
                "Hertz",
                "Avis",
                "Budget"
            ],
            "Preferred Car Brand": [
                "BMW",
                "Audi",
                "Mercedes-Benz"
            ],
            "Rental Duration Preference": "1-2 weeks",
            "Additional Feature Preference": [
                "navigation",
                "all-wheel drive"
            ],
            "Preferred Fuel Type": "gasoline"
        },
        "Restaurants": {
            "Cuisine Preference": [
                "Mediterranean",
                "Lebanese",
                "Turkish",
                "Moroccan"
            ],
            "Dietary Restrictions": [
                "kosher"
            ],
            "Ambiance Preference": [
                "casual",
                "outdoor seating"
            ],
            "Price Range": [
                "moderate",
                "budget-friendly"
            ]
        },
        "Services": {
            "Preferred Service Provider Types": "local",
            "Appointment Time Preference": [
                "evening",
                "morning"
            ],
            "Location Preference": [
                "near home",
                "within walking distance"
            ],
            "Service Frequency Preference": [
                "monthly",
                "one-off"
            ],
            "Service Provider Gender Preference": "no preference"
        },
        "Shopping": {
            "Preferred Product Category": [
                "fitness equipment",
                "outdoor & camping",
                "sports",
                "health & wellness"
            ],
            "Price Range Preference": "mid-range",
            "Brand Preference": [
                "Local Israeli brands",
                "Sustainable and eco-friendly brands"
            ]
        },
        "Sports": {
            "Favorite Sports": [
                "soccer",
                "basketball",
                "tennis"
            ],
            "Favorite Team": [
                "Maccabi Tel Aviv Basketball Club",
                "Israel National Soccer Team"
            ],
            "Viewing Preference": "live"
        },
        "Train": {
            "Preferred Train Class": "standard class",
            "Travel Time Preference": [
                "morning",
                "afternoon"
            ],
            "Amenity Preference": [
                "WiFi",
                "power outlet"
            ],
            "Preferred Seat Type": "aisle"
        },
        "Travel": {
            "Preferred Destination Types": [
                "historical",
                "cultural",
                "scenic",
                "beach"
            ],
            "Duration Preference": [
                "1-2 weeks",
                "3-4 weeks"
            ],
            "Group Size Preference": [
                "couple",
                "family"
            ],
            "Frequent Travel Destination": [
                "Greece",
                "Italy",
                "Turkey"
            ],
            "Travel Season Preference": [
                "Spring",
                "Fall"
            ]
        }
    },
    "demographics": {
        "user_id": "user419",
        "age": "35-44 years old",
        "gender": "Male",
        "employment_status": "Working part-time",
        "education": "Completed Secondary School",
        "marital_status": "Married",
        "english_proficiency": "Advanced",
        "ethnicity": "Middle Eastern / Arab",
        "religion": "Non-religious",
        "birth_country": "Israel",
        "reside_country": "Israel"
    },
    "interests": {
        "Alarm": 1,
        "Books": 1,
        "Buses": 0,
        "Calendar": 1,
        "Events": 1,
        "Finance": 1,
        "Flights": 0,
        "Games": 1,
        "Hotels": 1,
        "Media": 1,
        "Messaging": 1,
        "Movies": 1,
        "Music": 1,
        "Rental Cars": 1,
        "Restaurants": 1,
        "Services": 1,
        "Shopping": 1,
        "Sports": 1,
        "Train": 0,
        "Travel": 1
    },
    "interactions": {
        "Alarm": "The user, a 35-44 year old married male from Israel working part-time, has frequently engaged with the alarm domain to manage his daily schedule. Past interactions reveal a preference for setting a recurring weekday alarm at 8:30 AM, with a gentle nature sound to ease him into the morning.\n\nInitially, the user requested a simple alarm setup with the default sound, but over time, he experimented with various tones to find the most soothing option. He expressed frustration with jarring alarm sounds, leading the assistant to recommend nature-inspired melodies like bird songs or ocean waves.\n\nThe user appreciates the ability to customize snooze intervals and alarm volumes based on his sleep patterns. On occasion, he has asked the assistant to set temporary alarms for important appointments or reminders outside his regular weekday routine.\n\nAs his work schedule became more flexible, the user sought guidance on adjusting his alarm times accordingly, sometimes requesting earlier or later wake-up calls depending on his commitments. He values the assistant's ability to remember his preferences and make appropriate suggestions based on his routines.\n\nOver time, the user has explored additional features like gradually increasing alarm volumes and integrating weather updates or traffic information into his morning routine. He has also inquired about setting location-based alarms for when he travels, ensuring he doesn't oversleep or miss important events.\n\nThroughout their interactions, the user has maintained a polite and straightforward communication style, appreciating the assistant's clear and concise responses. He has occasionally provided feedback on the alarm experience, suggesting improvements or expressing satisfaction with specific features or customization options.",
        "Books": "The user, a 35-44 year old part-time working male from Israel, has a deep interest in exploring books across various genres, with a particular affinity for history, non-fiction, and biographies. Past interactions with the assistant have revolved around discovering and discussing thought-provoking works by authors such as Yuval Noah Harari, Amos Oz, and Sami Michael.\n\nIn one instance, the user sought recommendations for books similar to Harari's \"Sapiens: A Brief History of Humankind,\" leading to a curated list of engaging historical narratives and anthropological studies. They also expressed a keen interest in Amos Oz's \"A Tale of Love and Darkness,\" sparking a discussion about the author's unique storytelling style and insights into Israeli society.\n\nThe user has a preference for both physical and ebook formats, often requesting summaries or excerpts to gauge their interest before committing to a full read. They tend to engage with books in the evening, seeking immersive experiences that transport them to different eras or perspectives.\n\nOver time, the user has developed a particular fondness for Ken Follett's \"The Century Trilogy,\" leading to requests for similar multi-generational sagas that blend historical events with compelling character arcs. They have also sought recommendations for thought-provoking biographies, expressing a desire to gain deeper insights into the lives and motivations of influential figures.\n\nThe user values the assistant's ability to provide nuanced book analyses, drawing connections between different works and highlighting themes or perspectives that resonate with their interests. They appreciate concise summaries that capture the essence of a book, allowing them to make informed decisions about their reading choices.\n\nAdditionally, the user has shown an interest in participating in virtual book clubs or discussion forums, seeking opportunities to engage with like-minded individuals and explore diverse perspectives on the books they have read. They value the assistant's ability to facilitate such discussions, providing relevant context and fostering an environment for respectful and insightful exchanges.",
        "Buses": "The user, a 35-44 year old married male from Israel working part-time, frequently interacts with the assistant to manage his bus travel needs within the country. As a non-religious individual with an advanced level of English proficiency, he prefers a direct and efficient communication style.\n\nPast interactions have primarily revolved around finding and booking bus tickets with Egged and Dan, the user's preferred bus companies. He often requests morning or afternoon departure times and has a strong preference for window seats, which the assistant has learned to prioritize.\n\nIn one instance, the user asked the assistant to compare different bus routes and schedules for a weekly commute between Tel Aviv and Jerusalem, seeking the most convenient option. The assistant provided a detailed comparison, including travel times, number of stops, and fare prices, ultimately recommending the most efficient route based on the user's preferences.\n\nOver time, the user has developed a habit of checking bus schedules and purchasing tickets through the assistant, appreciating the convenience and personalized recommendations. He has also requested the assistant to set reminders for upcoming bus trips and provide real-time updates on any delays or schedule changes.\n\nThe user values the assistant's ability to understand his travel patterns and preferences, allowing for seamless and personalized bus travel experiences. He has expressed satisfaction with the assistant's direct communication style and has occasionally provided feedback to improve the accuracy of route suggestions or clarify preferences.\n\nAs his trust in the assistant's capabilities grew, the user began exploring additional features, such as requesting information on bus amenities (e.g., Wi-Fi availability, restrooms) and inquiring about discounted fares or loyalty programs offered by the bus companies.",
        "Calendar": "The user, a 35-44 year old married male from Israel working part-time, frequently interacts with the virtual assistant to manage his calendar and schedule various events. He has an advanced proficiency in English and prefers to receive notifications one day before scheduled events.\n\nOne recurring theme is coordinating family gatherings, such as birthdays, anniversaries, and holiday celebrations. The user often asks the assistant to set reminders for these events and requests suggestions for suitable venues or activity ideas to make the occasions more memorable.\n\nWork-related meetings also feature prominently in the user's calendar interactions. He relies on the assistant to schedule recurring team meetings, client calls, and project deadlines, ensuring he stays organized and doesn't miss important professional commitments.\n\nSocial events, such as catching up with friends or attending local community events, are another area of interest. The user appreciates recommendations for nearby happenings that align with his interests and frequently asks the assistant to block off time for these activities in his calendar.\n\nOver time, the user has developed a preference for a more conversational tone when interacting with the assistant. He values personalized suggestions and has expressed interest in the assistant's ability to learn from his past event preferences and scheduling patterns.\n\nAdditionally, the user has requested the integration of his calendar with other productivity tools, such as task managers and note-taking apps, to streamline his workflow and ensure seamless coordination between various aspects of his life.",
        "Events": "The user, a 35-44 year old married male from Israel working part-time, frequently interacts with the assistant to discover and attend local events in the cultural, food, and arts domains. His interactions often revolve around finding affordable, weekend events suitable for small groups.\n\nIn the past, the user has requested recommendations for cultural celebrations and food tastings in his area, preferring events under $50 or free admission. He has shown a particular interest in Middle Eastern and Mediterranean cuisine, asking for suggestions on upcoming food festivals or workshops exploring regional flavors.\n\nThe user has also sought out information on art exhibitions and lectures, especially those focused on contemporary Israeli or Middle Eastern artists. He values detailed event descriptions, including information on the featured artists, themes, and any interactive components.\n\nOver time, the user's interactions have evolved to include requests for event reminders and ticket purchasing assistance. He appreciates the ability to seamlessly purchase general admission tickets through the assistant, often for events on Friday evenings or Saturdays.\n\nThe user's tone is friendly and inquisitive, and he values concise yet informative responses. He has provided positive feedback when the assistant accurately captures his preferences for small group events with an educational or cultural component. Additionally, he has expressed interest in receiving personalized event recommendations based on his past attendance and preferences, particularly for unique or lesser-known events in his local community.",
        "Finance": "The user, a 35-44 year old married male from Israel, working part-time, has a keen interest in tracking financial markets and staying informed about the latest developments in the technology, healthcare, and consumer goods sectors. Past interactions with the virtual assistant have revolved around monitoring stock prices, accessing news updates, and seeking professional analyses for companies like Apple, Pfizer, Unilever, and local Israeli tech startups.\n\nThe user frequently requests real-time stock quotes and market updates for these companies, particularly during significant events like earnings reports or product launches. They often ask the assistant to consolidate news from various financial websites, investment newsletters, and professional analyses, seeking a comprehensive understanding of market trends and expert opinions.\n\nOver time, the user has expressed a growing interest in exploring investment opportunities within the Israeli tech startup ecosystem. They have requested the assistant to curate information on promising local startups, their funding rounds, and potential growth prospects. This has led to discussions about risk assessment, valuation metrics, and the impact of geopolitical factors on the regional tech landscape.\n\nThe user values concise, data-driven insights and appreciates visualizations that highlight key performance indicators and stock price movements. They have a preference for objective analyses and tend to cross-reference information from multiple sources before making investment decisions.\n\nIn addition to stock tracking, the user has shown an interest in understanding broader economic trends and their implications for various sectors. They have asked the assistant to provide updates on global events, such as regulatory changes, trade policies, or technological advancements, that could impact their investment portfolio.\n\nThe user's interactions often reflect a pragmatic and analytical approach, with a focus on maximizing returns while mitigating risks. They appreciate the assistant's ability to tailor information to their specific interests and preferences, while maintaining a professional and objective tone.",
        "Flights": "The user, a 35-44 year old married male from Israel with advanced English proficiency, has frequently engaged with the virtual assistant to search for and book flights. As a part-time worker, he values convenience and seeks efficient travel solutions.\n\nOver the course of numerous interactions, the user has consistently expressed a preference for booking economy or premium economy seats with aisle access on airlines such as El Al, Turkish Airlines, and Emirates. He favors morning or afternoon departures and prefers non-stop flights or those with short layovers to minimize travel time.\n\nIn one instance, the user requested assistance in finding the most affordable roundtrip flight from Tel Aviv to London during a specific date range. The assistant provided multiple options, highlighting the best deals based on the user's preferred airlines and layover preferences. After reviewing the options, the user booked a non-stop flight with El Al, opting for premium economy seats for added comfort.\n\nOn another occasion, the user sought help in coordinating a multi-city trip to Europe, with stops in Amsterdam, Berlin, and Prague. The assistant suggested a flight itinerary that minimized layovers and offered competitive pricing on Turkish Airlines, aligning with the user's preferences. The user appreciated the personalized recommendations and the assistant's ability to consolidate flight options based on his travel criteria.\n\nOver time, the user has developed a rapport with the assistant, often providing feedback on the booking experience and expressing gratitude for the personalized service. He has also requested assistance with managing flight changes or cancellations, relying on the assistant's expertise to navigate airline policies and procedures seamlessly.\n\nThe user's interactions reflect a desire for efficiency, value, and personalized travel solutions. He values the assistant's ability to understand and cater to his specific preferences, streamlining the flight booking process and ensuring a comfortable travel experience.",
        "Games": "The user, a 35-44 year old married male from Israel working part-time, has a keen interest in video games, particularly strategy, simulation, RPG, and puzzle genres. Past interactions with the assistant have centered around exploring new game titles, finding deals, and seeking recommendations tailored to his preferences.\n\nOne recurring theme has been the user's fascination with the Civilization series, frequently inquiring about the latest expansions, mods, and strategy guides for Civilization VI. He has also requested comparisons between Civilization VI and other popular strategy games like Europa Universalis IV or Total War: Warhammer II.\n\nThe user has shown a particular fondness for city-building and management simulation games like Cities: Skylines. He has sought advice on optimizing city layouts, managing resources, and troubleshooting common issues encountered in the game. Additionally, he has expressed interest in mods that enhance the game's realism or introduce new challenges.\n\nRPG games like The Witcher 3 have also been a topic of discussion, with the user seeking recommendations for similar open-world RPGs with rich storytelling and immersive environments. He has asked for guidance on completing side quests, finding hidden treasures, and maximizing character builds.\n\nPuzzle games like Portal 2 have been a source of enjoyment for the user, and he has inquired about other mind-bending puzzle games that offer a unique challenge and clever level design.\n\nOver time, the user has become more interested in online multiplayer experiences, seeking recommendations for games with active communities and competitive modes. He has requested information on joining gaming communities, participating in tournaments, and improving his skills in multiplayer strategy games.\n\nThe user values concise and informative responses, often asking for pros and cons, system requirements, and user reviews when considering new game purchases. He appreciates recommendations that align with his preferences for immersive storytelling, challenging gameplay, and replayability. Additionally, he has shown interest in gaming news, updates, and industry trends, particularly those related to his preferred genres and platforms.",
        "Hotels": "Here is a realistic interaction summary for the user based on the provided demographic profile and domain affinities:\n\nThe user, a 35-44 year old married male from Israel working part-time, frequently engages with the virtual assistant to book hotel accommodations that align with his preferences. Over time, a pattern has emerged where he gravitates towards upscale hotel chains like Radisson, Hyatt, and Intercontinental when planning trips within Israel or abroad.\n\nHis interactions often begin with a search for 4 or 5-star hotels in city centers or near major cultural attractions and shopping districts. The user values hotel amenities like complimentary WiFi, free breakfast, a pool, gym facilities, and an on-site bar or lounge area. He tends to inquire about room options, expressing a preference for double rooms or suites to accommodate his married status.\n\nIn one instance, the user requested recommendations for a week-long stay in Tel Aviv, prioritizing hotels within walking distance of the city's renowned Bauhaus architecture and lively nightlife scene. The assistant provided a curated list of options from preferred chains like the Intercontinental David Tel Aviv and Radisson Blu, complete with room rates, amenity details, and proximity to points of interest.\n\nFor an upcoming trip to Istanbul, the user sought a luxurious hotel near the historic Sultanahmet district and the iconic Hagia Sophia. After evaluating several options, he settled on the Radisson Blu Pera, drawn by its rooftop pool, central location, and positive reviews from fellow Israeli travelers.\n\nThroughout these interactions, the user's advanced English proficiency allows for clear communication of his needs and preferences. He appreciates concise summaries with relevant details like room rates, cancellation policies, and distance to nearby attractions. The assistant has learned to proactively highlight amenities matching his stated preferences, such as complimentary breakfast and well-equipped fitness centers.\n\nOver time, the user has occasionally expressed interest in exploring unique boutique hotels or properties with rich cultural heritage, suggesting a willingness to deviate from his usual chain preferences for truly exceptional experiences. His interactions reflect a desire for comfort, convenience, and an authentic sense of place during his travels.",
        "Media": "The user, a 35-44 year old married male from Israel with an advanced English proficiency, has a keen interest in exploring diverse media content, particularly in the realm of drama, historical fiction, foreign films, and independent productions. Past interactions with the assistant have revolved around discovering and accessing thought-provoking movies and TV shows across various streaming platforms.\n\nOne recurring theme has been the user's affinity for Iranian cinema, often seeking recommendations for critically acclaimed works by directors like Asghar Farhadi. The assistant has provided personalized suggestions, such as \"The Salesman\" and \"A Separation,\" which resonated deeply with the user's appreciation for nuanced storytelling and cultural exploration.\n\nAdditionally, the user has frequently requested guidance on navigating the vast catalogs of platforms like Netflix, Amazon Prime, and Kanopy to uncover hidden gems within their preferred genres. They have expressed a particular fondness for films that offer profound insights into human experiences and societal complexities, often favoring character-driven narratives over mainstream blockbusters.\n\nOver time, the user has sought recommendations for thought-provoking foreign films and independent productions, leading the assistant to curate lists featuring works like \"Persepolis\" and films starring actors like Golshifteh Farahani and Navid Mohammadzadeh. The user has consistently provided feedback on the recommendations, allowing the assistant to refine its understanding of their preferences further.\n\nThe interactions have evolved to include discussions about the deeper themes and symbolism present in the recommended media, with the user often engaging in analytical discourse and seeking the assistant's perspective on the artistic merits and cultural significance of certain works. They have also expressed interest in exploring related literature or documentaries that provide additional context or background information on the films and their creators.\n\nThroughout these interactions, the user has demonstrated a preference for concise yet insightful summaries and analyses, valuing the assistant's ability to distill complex narratives and themes into succinct overviews. They have also appreciated the assistant's ability to suggest complementary media recommendations based on their viewing history and expressed interests, fostering a dynamic and enriching exploration of diverse cinematic experiences.",
        "Messaging": "The user, a 35-44 year old married male from Israel working part-time, frequently engages with the virtual assistant to facilitate communication through various messaging apps. His preferred platforms are WhatsApp, Facebook Messenger, and Telegram, which he primarily uses to stay connected with family members and close friends.\n\nPast interactions often involve sending text messages to loved ones, either to share updates, coordinate plans, or simply maintain regular contact. The user appreciates the assistant's ability to quickly draft casual, informal messages that align with his relaxed communication style.\n\nFor example, he has asked the assistant to compose lighthearted check-in messages for his siblings living abroad, inquiring about their well-being while injecting a touch of humor. Similarly, he has requested messages to coordinate family gatherings or outings with friends, ensuring the tone remains friendly and conversational.\n\nOver time, the user has also leveraged the assistant's location-sharing capabilities, particularly when meeting up with friends or coordinating pickups and drop-offs within his local area. He values the convenience of sharing his real-time location without the need for lengthy explanations or directions.\n\nAdditionally, the user has occasionally sought guidance on navigating the various features and settings of his preferred messaging apps, such as customizing notification preferences or exploring new functionalities like voice messages or video calls.\n\nWhile the user primarily communicates via text, he has shown interest in exploring alternative modes of communication, such as voice notes or short video clips, especially when conveying more nuanced or emotional messages to close family members.\n\nThroughout these interactions, the user has consistently appreciated the assistant's ability to adapt to his casual, informal communication style while maintaining a friendly and personable demeanor.",
        "Movies": "The user, a 35-44 year old married, part-time working male from Israel, has a keen interest in movies, particularly in the drama, foreign film, historical fiction, and independent genres. Past interactions with the assistant have centered around exploring movie options available in theaters, seeking recommendations tailored to his preferences, and purchasing tickets for upcoming showings.\n\nOne recurring theme has been the user's affinity for Israeli filmmakers and actors, such as Amos Gitai, Natalie Portman, and Gal Gadot. He often inquires about their latest projects and seeks out critically acclaimed films featuring their work. The assistant has provided personalized suggestions, highlighting relevant movie synopses, reviews, and showtimes at local theaters.\n\nThe user prefers to watch movies on weekends or during vacations, typically in the evenings. He has a strong preference for standard or open-air cinema experiences and favors middle row, aisle seats for optimal viewing. The assistant has assisted in locating theaters that accommodate these preferences and has facilitated ticket purchases for the user's desired showtimes.\n\nOver time, the user has developed a deeper appreciation for thought-provoking, character-driven narratives that explore complex themes or offer unique cultural perspectives. He has requested recommendations for lesser-known independent films or foreign language movies that have garnered critical acclaim at international film festivals.\n\nThe user values concise yet informative movie summaries, highlighting key elements such as the director's vision, cinematography, and performances. He appreciates when the assistant provides context by drawing parallels to other films he has enjoyed or by highlighting the movie's cultural significance.\n\nAdditionally, the user has shown interest in attending special screenings, film festivals, or Q&A sessions with directors or actors, seeking immersive experiences that deepen his understanding and appreciation of the craft. The assistant has facilitated the discovery and booking of such events, aligning with the user's evolving interests and preferences.",
        "Music": "The user, a 35-44 year old married male from Israel working part-time, has a diverse taste in music and frequently engages with the assistant to discover new songs and albums across various genres. He has an advanced proficiency in English and a particular interest in rock, metal, electronic, and world music.\n\nPast interactions have involved requesting recommendations for Israeli rock bands like Orphaned Land and Mashina, whose albums \"El Norra Alila\" and \"Mabool\" are among his favorites. He often asks for playlists combining these genres, especially for workouts or studying sessions.\n\nThe user appreciates the assistant's ability to curate personalized playlists that blend his preferred artists, such as Lenny Kravitz and Infected Mushroom, with new discoveries. He has a strong preference for high-definition audio quality and primarily uses Spotify and YouTube Music for streaming.\n\nOver time, the user has shown an increasing interest in exploring world music genres, seeking recommendations for artists and albums that fuse diverse cultural influences. He values the assistant's ability to provide context and background information on the artists and their musical styles.\n\nThe user frequently requests updates on new album releases from his favorite bands and artists, as well as concert or tour information in Israel or neighboring regions. He has also asked for suggestions on music festivals or events that align with his eclectic tastes.\n\nWhile the user appreciates the assistant's recommendations, he also enjoys providing feedback on the suggested tracks or albums, often leading to engaging discussions about the nuances of different musical genres and their cultural significance.",
        "Rental Cars": "The user, a 35-44 year old married male from Israel working part-time, has engaged with the virtual assistant multiple times to book rental cars for various trips. His interactions reflect a preference for premium SUV rentals from major companies like Hertz, Avis, and Budget.\n\nIn past interactions, the user has frequently requested quotes and availability for high-end SUV models from brands like BMW, Audi, and Mercedes-Benz. He typically books rentals for 1-2 week durations and prioritizes features like navigation systems and all-wheel drive capabilities. The user has a strong preference for gasoline-powered vehicles.\n\nOver time, the user has developed a pattern of providing detailed feedback on his rental experiences, highlighting aspects he appreciated or areas for improvement. He has commended the assistant's ability to secure upgrades or discounts on preferred vehicle models.\n\nThe user values clear communication and expects prompt responses to inquiries about rental policies, pricing, and vehicle specifications. He has occasionally requested comparisons between rental companies or vehicle options to make informed decisions.\n\nWhile the user's tone is generally polite and straightforward, he has expressed frustration when faced with limited availability or pricing discrepancies. In such cases, he appreciates the assistant's efforts to offer alternative solutions or escalate concerns to customer service.\n\nAs the user's trust in the assistant has grown, he has started exploring options for longer rental periods (3-4 weeks) and has shown interest in electric or hybrid vehicle offerings, though his primary preference remains premium gasoline SUVs from reputable rental brands.",
        "Restaurants": "The user, a 35-44 year old married male from Israel working part-time, has frequently engaged with the assistant to discover and reserve restaurants that align with his preferences for Mediterranean, Lebanese, Turkish, and Moroccan cuisines. As a non-religious individual with an advanced proficiency in English, he values the assistant's ability to provide recommendations adhering to kosher dietary restrictions.\n\nEarly interactions focused on finding casual, budget-friendly restaurants with outdoor seating options in his local area. The user often requested suggestions for family-friendly establishments suitable for dining with his spouse and children. He appreciated the assistant's detailed descriptions of ambiance, menu highlights, and pricing to help narrow down choices.\n\nOver time, the user began exploring a wider range of cuisines within the Mediterranean sphere, seeking out unique regional specialties and hidden gems. He requested recommendations for authentic Turkish mezes and Lebanese mezze platters, expressing interest in vegetarian and vegan-friendly options that still maintained kosher standards.\n\nThe user has provided positive feedback on the assistant's ability to filter results based on his specific dietary needs, saving him time and effort. He has also inquired about making reservations directly through the assistant and has asked for tips on navigating kosher dining options when traveling abroad.\n\nIn recent interactions, the user has shown a growing curiosity about Moroccan cuisine, requesting recommendations for restaurants specializing in flavorful tagines and couscous dishes. He has expressed a preference for detailed menu descriptions, highlighting standout dishes and accommodations for dietary restrictions.\n\nThroughout the interactions, the user has maintained a friendly and inquisitive tone, often providing feedback on his dining experiences and seeking clarification or additional details when needed. He values the assistant's efficient and personalized approach, tailored to his unique culinary preferences and lifestyle needs.",
        "Services": "The user, a 35-44 year old married male residing in Israel, has frequently engaged with the assistant to book appointments with local service providers for various needs. As a part-time worker, he prefers scheduling appointments during evenings or mornings for convenience.\n\nFor routine services like haircuts and dental cleanings, the user has established a pattern of booking monthly appointments at familiar providers within walking distance from his home. He values the assistant's ability to suggest available time slots and send reminders for these recurring appointments.\n\nIn one instance, the user requested recommendations for a reliable local mechanic to service his car. The assistant provided a curated list of highly-rated options near his neighborhood, along with their operating hours and pricing information. The user appreciated the detailed comparisons and ultimately booked an appointment for a convenient evening slot.\n\nWhen seeking one-off services like home repairs or medical consultations, the user has relied on the assistant to provide a comprehensive overview of providers, including reviews, qualifications, and service descriptions. He has expressed a preference for clear and concise summaries, allowing him to make informed decisions efficiently.\n\nOver time, the user has developed a rapport with the assistant, occasionally providing feedback on the quality of service received or requesting adjustments for future appointments. He has also inquired about the possibility of bundling services for discounted rates or package deals.\n\nWhile the user does not have a specific gender preference for service providers, he has shown an appreciation for the assistant's ability to accommodate any special requests or dietary restrictions when booking appointments at restaurants or catering services.",
        "Shopping": "The user, a 35-44 year old married male from Israel working part-time, frequently engages with the assistant to explore fitness equipment, outdoor gear, sports products, and wellness items. Past interactions reveal a strong preference for mid-range local Israeli brands, with a focus on sustainable and eco-friendly options.\n\nInitially, the user sought recommendations for home workout equipment suitable for small spaces, leading to discussions about compact treadmills, resistance bands, and adjustable dumbbells. Over time, their interests expanded to outdoor pursuits like camping and hiking, prompting requests for lightweight tents, sleeping bags, and hydration packs from Israeli brands like Klarna and Zofim.\n\nThe user values detailed product specifications, user reviews, and comparative analyses to make informed decisions. They often ask for side-by-side comparisons of similar products, focusing on durability, eco-friendliness, and value for money. Interactions frequently involve clarifying technical details, such as weight capacity, material composition, or battery life.\n\nAs their fitness journey progressed, the user began exploring sports gear like yoga mats, resistance bands, and running shoes from sustainable brands like Naot and Arafa. They appreciated personalized recommendations based on their preferences for breathable fabrics and minimalist designs.\n\nOver time, the user's interests expanded to include health and wellness products, leading to discussions about organic skincare lines, plant-based supplements, and eco-friendly water bottles. They frequently seek out products with minimal packaging and ethical sourcing practices.\n\nThe user's tone is direct and inquisitive, often providing feedback on the assistant's recommendations and requesting additional details or alternatives. They value concise yet comprehensive responses and have expressed appreciation for the assistant's ability to tailor suggestions to their specific needs and values.",
        "Sports": "The user, a 35-44 year old married male from Israel working part-time, has a strong affinity for sports, particularly soccer, basketball, and tennis. Past interactions with the assistant have centered around accessing live scores, match schedules, and statistics for his favorite teams and players.\n\nOne of the user's primary interests is following the Maccabi Tel Aviv Basketball Club, Israel's most successful basketball team. He frequently requests live score updates during their Euroleague and domestic league games, as well as player statistics and injury reports. The user also closely tracks the performance of the Israel National Soccer Team, seeking match schedules, live scores, and post-game analysis during international tournaments and World Cup qualifiers.\n\nIn addition to his local teams, the user has a keen interest in major international soccer leagues, such as the English Premier League, La Liga, and Serie A. He often asks for live score updates, standings, and player rankings for these leagues, particularly during high-profile matches or towards the end of the season.\n\nThe user values timely and accurate information, preferring to receive live score updates and match notifications as events unfold. He has expressed a preference for concise, easy-to-digest statistics and has requested the assistant to provide visual representations, such as charts and graphs, for player and team performance metrics.\n\nOver time, the user's interactions have evolved to include requests for historical data and records, such as head-to-head statistics between teams or players, as well as predictions and analysis from sports experts and pundits. He has also shown interest in exploring alternative sports like tennis, particularly during major tournaments like Wimbledon or the US Open.\n\nThe user appreciates a conversational tone from the assistant, often engaging in friendly banter and exchanging opinions on controversial refereeing decisions or player transfers. He values the assistant's ability to provide unbiased, factual information while also offering insights and analysis that cater to his specific interests and preferences.",
        "Train": "The user, a 35-44 year old married male from Israel working part-time, frequently interacts with the assistant to book and manage train journeys within Israel. He has an advanced level of English proficiency and prefers standard class seating with amenities like WiFi and power outlets.\n\nPast interactions often involve booking morning or afternoon train trips, with a preference for aisle seats. The user typically requests the most convenient routes and schedules, prioritizing journey duration over cost. He occasionally inquires about discounted fares or promotions for frequent travelers.\n\nOver time, the user has developed a habit of checking train schedules and availability a few days in advance, allowing the assistant to provide timely updates on any delays or disruptions. He appreciates concise summaries of journey details, including platform numbers, estimated arrival times, and connection information if applicable.\n\nThe user has expressed a preference for receiving reminders and notifications about upcoming trips, particularly for journeys involving transfers or tight connections. He values the assistant's ability to suggest alternative routes or modes of transportation in case of significant delays or cancellations.\n\nIn addition to booking and managing trips, the user occasionally seeks recommendations for nearby cafes or restaurants with vegetarian options near major train stations. He has also inquired about luggage storage facilities and accessibility services for travelers with disabilities, possibly for future trips with family or friends.\n\nOverall, the user's interactions with the assistant reflect a practical and efficient approach to train travel, with a focus on reliable information, timely updates, and convenient amenities tailored to his preferences.",
        "Travel": "The user, a 35-44 year old married male from Israel with advanced English proficiency, has a keen interest in travel and exploring new destinations. Past interactions with the assistant have focused on planning trips to historical, cultural, and scenic locations, with a particular emphasis on destinations like Greece, Italy, and Turkey.\n\nFor a trip to Greece, the user requested an itinerary that balanced visits to ancient ruins and archaeological sites with opportunities to experience local cuisine and culture. The assistant provided recommendations for lesser-known islands like Naxos and Paros, in addition to must-see attractions in Athens and Delphi. The user appreciated the inclusion of family-friendly activities and accommodations suitable for couples.\n\nIn another instance, the user sought guidance for a 3-week trip to Italy, with a focus on immersing themselves in the country's rich history and art. The assistant curated a comprehensive itinerary that included visits to Rome, Florence, Venice, and smaller towns like Siena and Assisi. The user valued the assistant's ability to suggest off-the-beaten-path experiences, such as attending a cooking class in Tuscany or exploring the ruins of Pompeii.\n\nFor trips to Turkey, the user has requested a balance of cultural attractions, such as the Hagia Sophia and Topkapi Palace in Istanbul, with scenic destinations like Cappadocia and the Turquoise Coast. The assistant has provided recommendations for family-friendly resorts and activities, as well as tips for navigating the country during the preferred Spring and Fall travel seasons.\n\nOver time, the user has developed a preference for detailed itineraries that include a mix of guided tours and independent exploration. They have also expressed interest in sustainable tourism practices and have sought recommendations for eco-friendly accommodations and activities. The user appreciates the assistant's ability to tailor recommendations to their preferences while also suggesting unique experiences they may not have considered."
    }
}